damask_parse/__init__.py
damask_parse/_version.py
damask_parse/legacy/__init__.py
damask_parse/legacy/readers.py
damask_parse/legacy/writers.py
damask_parse/particles.py
damask_parse/quats.py
damask_parse/readers.py
damask_parse/rotation.py
damask_parse/utils.py
damask_parse/writers.py
damask_parse-0.4.1.dist-info/LICENSE
damask_parse-0.4.1.dist-info/METADATA
damask_parse-0.4.1.dist-info/WHEEL
damask_parse-0.4.1.dist-info/RECORD
